limengine/__init__.py
limengine/myfunctions.py
limengine-0.0.1.dist-info/METADATA
limengine-0.0.1.dist-info/WHEEL
limengine-0.0.1.dist-info/top_level.txt
limengine-0.0.1.dist-info/RECORD
