Metadata-Version: 2.1
Name: limengine
Version: 0.0.1
Summary: Pygame-based game engine
Home-page: UNKNOWN
Author: Enrike Churin
License: UNKNOWN
Keywords: pygame,game,game engine,graphics
Platform: UNKNOWN
Classifier: Development Status :: 1 - Planning
Classifier: Environment :: MacOS X
Classifier: Intended Audience :: Developers
Classifier: Intended Audience :: Education
Classifier: License :: OSI Approved :: MIT License
Classifier: Natural Language :: English
Classifier: Operating System :: MacOS
Classifier: Operating System :: MacOS :: MacOS X
Classifier: Operating System :: Microsoft :: Windows
Classifier: Operating System :: Microsoft :: Windows :: Windows 10
Classifier: Operating System :: OS Independent
Classifier: Operating System :: POSIX :: Linux
Classifier: Operating System :: Unix
Classifier: Programming Language :: Python :: 3 :: Only
Classifier: Topic :: Games/Entertainment
Classifier: Topic :: Software Development
Classifier: Topic :: Software Development :: Libraries :: pygame
Requires-Dist: pygame
